{
  "productionMode": false,
  "eagerServerLoad": false,
  "npmFolder": "C:\\Users\\Jordan Leich\\Documents\\GitHub\\Habit-Tracker-2.0",
  "node.version": "v18.14.1",
  "node.download.root": "https://nodejs.org/dist/",
  "generatedFolder": "C:\\Users\\Jordan Leich\\Documents\\GitHub\\Habit-Tracker-2.0\\target\\frontend",
  "frontendFolder": "C:\\Users\\Jordan Leich\\Documents\\GitHub\\Habit-Tracker-2.0\\frontend",
  "connect.javaSourceFolder": "C:\\Users\\Jordan Leich\\Documents\\GitHub\\Habit-Tracker-2.0\\src\\main\\java",
  "javaResourceFolder": "C:\\Users\\Jordan Leich\\Documents\\GitHub\\Habit-Tracker-2.0\\src\\main\\resources",
  "connect.applicationProperties": "C:\\Users\\Jordan Leich\\Documents\\GitHub\\Habit-Tracker-2.0\\src\\main\\resources\\application.properties",
  "connect.openApiFile": "C:\\Users\\Jordan Leich\\Documents\\GitHub\\Habit-Tracker-2.0\\target\\generated-resources\\openapi.json",
  "project.frontend.generated": "C:\\Users\\Jordan Leich\\Documents\\GitHub\\Habit-Tracker-2.0\\frontend\\generated",
  "pnpm.enable": false,
  "require.home.node": false,
  "build.folder": "target"
}
